tremolo_session/__init__.py
tremolo_session-1.0.13.dist-info/LICENSE
tremolo_session-1.0.13.dist-info/METADATA
tremolo_session-1.0.13.dist-info/WHEEL
tremolo_session-1.0.13.dist-info/top_level.txt
tremolo_session-1.0.13.dist-info/RECORD
