Metadata-Version: 2.1
Name: tremolo-session
Version: 1.0.13
Summary: A simple, file-based session middleware for Tremolo.
Author-email: Anggit Arfanto <contact@anggit.com>
License: MIT License
Project-URL: Homepage, https://github.com/nggit/tremolo-session
Project-URL: Source, https://github.com/nggit/tremolo-session
Project-URL: Funding, https://github.com/sponsors/nggit
Classifier: Development Status :: 4 - Beta
Classifier: Intended Audience :: Developers
Classifier: License :: OSI Approved :: MIT License
Classifier: Operating System :: OS Independent
Classifier: Topic :: Software Development :: Libraries :: Application Frameworks
Requires-Python: >=3.6
License-File: LICENSE
Requires-Dist: tremolo>=0.4.8
